ConsentiumThingsPy/__init__.py
ConsentiumThingsPy/consentiumthings.py
ConsentiumThingsPy-0.0.5.dist-info/METADATA
ConsentiumThingsPy-0.0.5.dist-info/WHEEL
ConsentiumThingsPy-0.0.5.dist-info/top_level.txt
ConsentiumThingsPy-0.0.5.dist-info/RECORD
