Metadata-Version: 2.1
Name: ConsentiumThingsPy
Version: 0.0.5
Summary: Sending sensor data to IoT server
Author: Debjyoti Chowdhury, Ph.D.
Author-email: <consentium.inc@gmail.com>
Keywords: Python,Internet of Things
Classifier: Development Status :: 1 - Planning
Classifier: Intended Audience :: Developers
Classifier: Programming Language :: Python :: 3
Classifier: Operating System :: Unix
Classifier: Operating System :: MacOS :: MacOS X
Classifier: Operating System :: Microsoft :: Windows
Requires-Dist: requests
